orchestra_sdk/__init__.py
orchestra_sdk/check_environment.py
orchestra_sdk/enum.py
orchestra_sdk/errors.py
orchestra_sdk/http.py
orchestra_sdk/orchestra.py
orchestra_sdk-0.1.1.dist-info/licenses/LICENSE.md
orchestra_sdk-0.1.1.dist-info/METADATA
orchestra_sdk-0.1.1.dist-info/WHEEL
orchestra_sdk-0.1.1.dist-info/top_level.txt
orchestra_sdk-0.1.1.dist-info/RECORD
