Metadata-Version: 2.4
Name: orchestra-sdk
Version: 0.1.1
Summary: Orchestra SDK for updating self-hosted Tasks.
Author-email: Orchestra Technologies <support@getorchestra.io>
License: Copyright 2025 Orchestra Technologies
Keywords: python,logging,data,orchestration
Classifier: Development Status :: 4 - Beta
Classifier: Intended Audience :: Developers
Classifier: License :: OSI Approved :: MIT License
Classifier: Topic :: Database
Requires-Python: >=3.8.0
License-File: LICENSE.md
Requires-Dist: requests
Requires-Dist: tenacity
Provides-Extra: dev
Requires-Dist: black; extra == "dev"
Requires-Dist: build; extra == "dev"
Requires-Dist: pyright; extra == "dev"
Requires-Dist: pytest; extra == "dev"
Requires-Dist: pytest-mock; extra == "dev"
Requires-Dist: responses; extra == "dev"
Requires-Dist: ruff; extra == "dev"
Requires-Dist: twine; extra == "dev"
Dynamic: license-file
